{"cameraMode":{"drawMode":0,"name":"Shaded","section":"Shading Mode"},"sceneLighting":true,"audioPlay":false,"sceneViewState":{"m_AlwaysRefresh":false,"showFog":true,"showSkybox":true,"showFlares":true,"showImageEffects":true,"showParticleSystems":true,"showVisualEffectGraphs":true,"m_FxEnabled":true},"in2DMode":false,"pivot":{"x":-2.388800859451294,"y":1.468498945236206,"z":0.7805726528167725},"rotation":{"x":-0.09226524829864502,"y":-0.841296374797821,"z":0.1520557403564453,"w":-0.5104861259460449},"size":2.2242112159729006,"orthographic":false}